scikit_deploy/__init__.py
scikit_deploy/__main__.py
scikit_deploy/build.py
scikit_deploy/main.py
scikit_deploy/__pycache__/__init__.cpython-36.pyc
scikit_deploy/__pycache__/__main__.cpython-36.pyc
scikit_deploy/__pycache__/build.cpython-36.pyc
scikit_deploy/__pycache__/main.cpython-36.pyc
scikit_deploy/scikit_deploy_server/Dockerfile
scikit_deploy/scikit_deploy_server/Dockerfile-multi-stage
scikit_deploy/scikit_deploy_server/__init__.py
scikit_deploy/scikit_deploy_server/main.py
scikit_deploy/scikit_deploy_server/main.py.6c001c700fb17d12feb21c10726ca058.py
scikit_deploy/scikit_deploy_server/requirements.txt
scikit_deploy/scikit_deploy_server/validate.py
scikit_deploy/scikit_deploy_server/__pycache__/__init__.cpython-36.pyc
scikit_deploy/scikit_deploy_server/__pycache__/main.cpython-36.pyc
scikit_deploy/scikit_deploy_server/server/__init__.py
scikit_deploy/scikit_deploy_server/server/config.py
scikit_deploy/scikit_deploy_server/server/endpoint.py
scikit_deploy/scikit_deploy_server/server/logging.py
scikit_deploy/scikit_deploy_server/server/prediction.py
scikit_deploy/scikit_deploy_server/server/scoring.py
scikit_deploy/scikit_deploy_server/server/util.py
scikit_deploy/scikit_deploy_server/server/__pycache__/__init__.cpython-36.pyc
scikit_deploy/scikit_deploy_server/server/__pycache__/config.cpython-36.pyc
scikit_deploy/scikit_deploy_server/server/__pycache__/logging.cpython-36.pyc
scikit_deploy/scikit_deploy_server/server/__pycache__/prediction.cpython-36.pyc
scikit_deploy/scikit_deploy_server/server/__pycache__/scoring.cpython-36.pyc
scikit_deploy/scikit_deploy_server/server/__pycache__/util.cpython-36.pyc
scikit_deploy/scikit_deploy_server/server/resources/__init__.py
scikit_deploy/scikit_deploy_server/server/resources/clf.pkl
scikit_deploy/scikit_deploy_server/server/resources/config.json
scikit_deploy-2.1.2.dist-info/LICENSE
scikit_deploy-2.1.2.dist-info/METADATA
scikit_deploy-2.1.2.dist-info/WHEEL
scikit_deploy-2.1.2.dist-info/entry_points.txt
scikit_deploy-2.1.2.dist-info/top_level.txt
scikit_deploy-2.1.2.dist-info/RECORD
