Metadata-Version: 2.1
Name: scikit-deploy
Version: 2.1.2
Summary: Scikit-learn model REST API deployment with docker
Home-page: https://github.com/fitle-dev/scikit-deploy
Author: Fitle
Author-email: nerds@fitle.com
License: UNKNOWN
Platform: UNKNOWN
Requires-Dist: docker
